Workbook

Sheet cover
A1: LBO Model Summary
A3: Company | B3: ='historicals_input'!$B11
A5: Key Outputs
A6: Metric | B6: Value
A7: Entry EV | B7: ='returns'!$B4
A8: Sponsor Equity | B8: ='returns'!$B9
A9: Exit EV | B9: ='returns'!$B13
A10: Exit Equity | B10: ='returns'!$B22
A11: MOIC | B11: ='returns'!$B23
A12: IRR | B12: ='returns'!$B24
A13: DCF Share Price | B13: ='valuation'!$E21
A16: Model Status
A17: Pass Count | B17: =COUNTIF(checks!C4:C13,"PASS")
A18: Fail Count | B18: =COUNTIF(checks!C4:C13,"FAIL")
A20: Workbook Tabs
A21: cover
A22: historicals_input
A23: assumptions
A24: debt_setup
A25: sources_uses
A26: operating_model
A27: debt_schedule
A28: returns
A29: valuation
A30: sensitivities
A31: checks
A32: dense_model

Sheet historicals_input
A1: Historicals & Input
A3: Historical Financials
A4: Year | B4: Revenue | C4: EBITDA | D4: EBITDA Margin | E4: Capex | F4: D&A | G4: NWC
A5: 2022 | B5: 2.70839e+10 | C5: 7.0229478e+09 | D5: 0.25930342 | E5: 4.875102e+08 | F5: 5.41678e+08 | G5: 2.70839e+08
A6: 2023 | B6: 2.8438095e+10 | C6: 7.6584762e+09 | D6: 0.26930342 | E6: 5.1188571e+08 | F6: 5.687619e+08 | G6: 2.8438095e+08
A7: 2024 | B7: 29860000000 | C7: 8340000000 | D7: 0.27930342 | E7: 537480000 | F7: 597200000 | G7: 298600000
A10: Core Inputs
A11: Company Name | B11: Example Media Company
A12: Shares Outstanding | B12: 783800000
A13: Entry EBITDA | B13: 8340000000
A14: Entry Multiple | B14: 10
A15: Debt-Free Acquisition (0/1) | B15: 0
A16: Existing Debt | B16: 23336000000
A17: Existing Cash | B17: 1000000000
A18: Transaction Fee % | B18: 0.02
A19: Financing Fee % | B19: 0.01
A20: OID % | B20: 0.02
A21: Management Rollover % | B21: 0
A22: Minimum Cash Balance | B22: 50000000
A24: Financing Assumptions
A25: Senior Debt / EBITDA | B25: 4
A26: Sub Debt / EBITDA | B26: 1
A27: Senior Interest Rate | B27: 0.06
A28: Senior Term % | B28: 0.7
A29: Senior TLA % | B29: 0.4
A30: Senior TLB % | B30: 0.6
A31: Sub Interest Rate | B31: 0.08
A32: Sub PIK Rate | B32: 0
A33: Revolver Rate | B33: 0.07
A34: Revolver Limit | B34: 6255000000
A35: Senior Amortization % | B35: 0.05
A36: Cash Sweep % | B36: 1
A38: Valuation Assumptions
A39: Tax Rate | B39: 0.25
A40: Risk Free Rate | B40: 0.042
A41: Beta | B41: 1.2
A42: Market Risk Premium | B42: 0.06
A43: Cost of Debt | B43: 0.065
A44: Terminal Growth | B44: 0.025
A45: Exit Multiple | B45: 10

Sheet assumptions
A1: Projection Assumptions
A3: Projection Assumptions by Year
A4: Metric | B4: 2025E | C4: 2026E | D4: 2027E | E4: 2028E | F4: 2029E
A5: Revenue Growth | B5: 0.05 | C5: 0.05 | D5: 0.05 | E5: 0.05 | F5: 0.05
A6: EBITDA Margin | B6: 0.28 | C6: 0.28 | D6: 0.28 | E6: 0.28 | F6: 0.28
A7: Capex % Revenue | B7: 0.018 | C7: 0.018 | D7: 0.018 | E7: 0.018 | F7: 0.018
A8: D&A % Revenue | B8: 0.02 | C8: 0.02 | D8: 0.02 | E8: 0.02 | F8: 0.02
A9: NWC % Revenue | B9: 0.01 | C9: 0.01 | D9: 0.01 | E9: 0.01 | F9: 0.01

Sheet debt_setup
A1: Debt Tranche Setup
A3: Debt Tranches
A4: Metric | B4: TLA | C4: TLB | D4: Sub Notes | E4: Revolver
A5: Target Multiple | B5: ='historicals_input'!$B25*'historicals_input'!$B29 | C5: ='historicals_input'!$B25*'historicals_input'!$B30 | D5: ='historicals_input'!$B26 | E5: =IFERROR('historicals_input'!$B34/'historicals_input'!$B13,0)
A6: Gross Debt | B6: ='historicals_input'!$B13*B5 | C6: ='historicals_input'!$B13*C5 | D6: ='historicals_input'!$B13*D5 | E6: ='historicals_input'!$B34
A7: OID % | B7: 0% | C7: ='historicals_input'!$B20 | D7: ='historicals_input'!$B20 | E7: 0%
A8: Net Funding | B8: =B6*(1-B7) | C8: =C6*(1-C7) | D8: =D6*(1-D7) | E8: =0
A9: Cash Interest Rate | B9: ='historicals_input'!$B27 | C9: ='historicals_input'!$B27 | D9: ='historicals_input'!$B31 | E9: ='historicals_input'!$B33
A10: PIK Rate | B10: 0% | C10: 0% | D10: ='historicals_input'!$B32 | E10: 0%
A11: Amortization % | B11: ='historicals_input'!$B35 | C11: 0% | D11: 0% | E11: 0%

Sheet sources_uses
A1: Sources & Uses
A3: Uses | D3: Capital Structure Bridge
A4: Line Item | B4: Amount | D4: Metric | E4: Value
A5: Purchase Price | B5: ='historicals_input'!$B13*'historicals_input'!$B14 | D5: Gross TLA | E5: ='debt_setup'!$B6
A6: Refinance Existing Debt | B6: =(1-'historicals_input'!$B15)*'historicals_input'!$B16 | D6: Gross TLB | E6: ='debt_setup'!$C6
A7: Transaction Fees | B7: =B5*'historicals_input'!$B18 | D7: Gross Sub | E7: ='debt_setup'!$D6
A8: Financing Fees | B8: =('debt_setup'!$B6+'debt_setup'!$C6+'debt_setup'!$D6)*'historicals_input'!$B19 | D8: OID Discount | E8: =SUM(E5:E7)-SUM(B14:B16)
A9: Minimum Cash | B9: ='historicals_input'!$B22 | D9: Total Net New Debt | E9: =SUM(B14:B16)
A10: Total Uses | B10: =SUM(B5:B9)
A12: Sources
A13: Line Item | B13: Amount
A14: TLA Net Debt | B14: ='debt_setup'!$B8
A15: TLB Net Debt | B15: ='debt_setup'!$C8
A16: Sub Debt | B16: ='debt_setup'!$D8
A17: Existing Cash | B17: ='historicals_input'!$B17
A18: Management Rollover | B18: =B5*'historicals_input'!$B21
A19: Sponsor Equity | B19: =B10-SUM(B14:B18)
A20: Total Sources | B20: =SUM(B14:B19)

Sheet operating_model
A1: Operating Model
A3: Metric | B3: 2025E | C3: 2026E | D3: 2027E | E3: 2028E | F3: 2029E | H3: Notes
A4: revenue | B4: ='historicals_input'!$B7*(1+'assumptions'!$B5) | C4: =B4*(1+'assumptions'!$C5) | D4: =C4*(1+'assumptions'!$D5) | E4: =D4*(1+'assumptions'!$E5) | F4: =E4*(1+'assumptions'!$F5) | H4: Excel is the source of truth. Python outputs are only safety checks.
A5: growth | B5: ='assumptions'!$B5 | C5: ='assumptions'!$C5 | D5: ='assumptions'!$D5 | E5: ='assumptions'!$E5 | F5: ='assumptions'!$F5
A6: ebitda_margin | B6: ='assumptions'!$B6 | C6: ='assumptions'!$C6 | D6: ='assumptions'!$D6 | E6: ='assumptions'!$E6 | F6: ='assumptions'!$F6
A7: ebitda | B7: =B4*B6 | C7: =C4*C6 | D7: =D4*D6 | E7: =E4*E6 | F7: =F4*F6
A8: da_pct | B8: ='assumptions'!$B8 | C8: ='assumptions'!$C8 | D8: ='assumptions'!$D8 | E8: ='assumptions'!$E8 | F8: ='assumptions'!$F8
A9: da | B9: =B4*B8 | C9: =C4*C8 | D9: =D4*D8 | E9: =E4*E8 | F9: =F4*F8
A10: ebit | B10: =B7-B9 | C10: =C7-C9 | D10: =D7-D9 | E10: =E7-E9 | F10: =F7-F9
A11: taxes | B11: =B10*'historicals_input'!$B39 | C11: =C10*'historicals_input'!$B39 | D11: =D10*'historicals_input'!$B39 | E11: =E10*'historicals_input'!$B39 | F11: =F10*'historicals_input'!$B39
A12: capex_pct | B12: ='assumptions'!$B7 | C12: ='assumptions'!$C7 | D12: ='assumptions'!$D7 | E12: ='assumptions'!$E7 | F12: ='assumptions'!$F7
A13: capex | B13: =B4*B12 | C13: =C4*C12 | D13: =D4*D12 | E13: =E4*E12 | F13: =F4*F12
A14: nwc_pct | B14: ='assumptions'!$B9 | C14: ='assumptions'!$C9 | D14: ='assumptions'!$D9 | E14: ='assumptions'!$E9 | F14: ='assumptions'!$F9
A15: nwc_balance | B15: =B4*B14 | C15: =C4*C14 | D15: =D4*D14 | E15: =E4*E14 | F15: =F4*F14
A16: delta_nwc | B16: =B15-'historicals_input'!$G7 | C16: =C15-B15 | D16: =D15-C15 | E16: =E15-D15 | F16: =F15-E15
A17: ufcf | B17: =B10-B11+B9-B13-B16 | C17: =C10-C11+C9-C13-C16 | D17: =D10-D11+D9-D13-D16 | E17: =E10-E11+E9-E13-E16 | F17: =F10-F11+F9-F13-F16

Sheet debt_schedule
A1: Debt Schedule
A3: Year | B3: Beg Cash | C3: Beg TLA | D3: Beg TLB | E3: Beg Sub | F3: Beg Revolver | G3: UFCF | H3: TLA Interest | I3: TLB Interest | J3: Sub Cash Interest | K3: Sub PIK | L3: Revolver Interest | M3: Cash Pre Debt Service | N3: TLA Mandatory | O3: Revolver Repay | P3: Cash Post Mandatory | Q3: Cash Sweep Capacity | R3: TLB Sweep | S3: TLA Sweep | T3: Sub Sweep | U3: Revolver Draw | V3: Liquidity Shortfall | W3: End Cash | X3: End TLA | Y3: End TLB | Z3: End Sub | AA3: End Revolver
A4: 2025 | B4: ='sources_uses'!$B9 | C4: ='sources_uses'!$B$14 | D4: ='sources_uses'!$B$15 | E4: ='sources_uses'!$B16 | F4: 0 | G4: ='operating_model'!$B17 | H4: =C4*'debt_setup'!$B9 | I4: =D4*'debt_setup'!$C9 | J4: =E4*'historicals_input'!$B31 | K4: =E4*'historicals_input'!$B32 | L4: =F4*'historicals_input'!$B33 | M4: =B4+G4-H4-I4-J4-L4 | N4: =MIN(C4*'debt_setup'!$B11,C4) | O4: =MIN(MAX(M4-N4-'historicals_input'!$B22,0),F4) | P4: =M4-N4-O4 | Q4: =MAX(P4-'historicals_input'!$B22,0)*'historicals_input'!$B36 | R4: =MIN(Q4,D4) | S4: =MIN(MAX(Q4-R4,0),MAX(C4-N4,0)) | T4: =MIN(MAX(Q4-R4-S4,0),E4+K4) | U4: =MIN(MAX('historicals_input'!$B22-(P4-R4-S4-T4),0),MAX('historicals_input'!$B34-F4+O4,0)) | V4: =MAX('historicals_input'!$B22-(P4-R4-S4-T4-U4),0) | W4: =P4-R4-S4-T4+U4 | X4: =MAX(C4-N4-S4,0) | Y4: =MAX(D4-R4,0) | Z4: =MAX(E4+K4-T4,0) | AA4: =MAX(F4-O4+U4,0)
A5: 2026 | B5: =U4 | C5: =V4 | D5: =W4 | E5: =X4 | F5: =Y4 | G5: ='operating_model'!$C17 | H5: =C5*'debt_setup'!$B9 | I5: =D5*'debt_setup'!$C9 | J5: =E5*'historicals_input'!$B31 | K5: =E5*'historicals_input'!$B32 | L5: =F5*'historicals_input'!$B33 | M5: =B5+G5-H5-I5-J5-L5 | N5: =MIN(C5*'debt_setup'!$B11,C5) | O5: =MIN(MAX(M5-N5-'historicals_input'!$B22,0),F5) | P5: =M5-N5-O5 | Q5: =MAX(P5-'historicals_input'!$B22,0)*'historicals_input'!$B36 | R5: =MIN(Q5,D5) | S5: =MIN(MAX(Q5-R5,0),MAX(C5-N5,0)) | T5: =MIN(MAX(Q5-R5-S5,0),E5+K5) | U5: =MIN(MAX('historicals_input'!$B22-(P5-R5-S5-T5),0),MAX('historicals_input'!$B34-F5+O5,0)) | V5: =MAX('historicals_input'!$B22-(P5-R5-S5-T5-U5),0) | W5: =P5-R5-S5-T5+U5 | X5: =MAX(C5-N5-S5,0) | Y5: =MAX(D5-R5,0) | Z5: =MAX(E5+K5-T5,0) | AA5: =MAX(F5-O5+U5,0)
A6: 2027 | B6: =U5 | C6: =V5 | D6: =W5 | E6: =X5 | F6: =Y5 | G6: ='operating_model'!$D17 | H6: =C6*'debt_setup'!$B9 | I6: =D6*'debt_setup'!$C9 | J6: =E6*'historicals_input'!$B31 | K6: =E6*'historicals_input'!$B32 | L6: =F6*'historicals_input'!$B33 | M6: =B6+G6-H6-I6-J6-L6 | N6: =MIN(C6*'debt_setup'!$B11,C6) | O6: =MIN(MAX(M6-N6-'historicals_input'!$B22,0),F6) | P6: =M6-N6-O6 | Q6: =MAX(P6-'historicals_input'!$B22,0)*'historicals_input'!$B36 | R6: =MIN(Q6,D6) | S6: =MIN(MAX(Q6-R6,0),MAX(C6-N6,0)) | T6: =MIN(MAX(Q6-R6-S6,0),E6+K6) | U6: =MIN(MAX('historicals_input'!$B22-(P6-R6-S6-T6),0),MAX('historicals_input'!$B34-F6+O6,0)) | V6: =MAX('historicals_input'!$B22-(P6-R6-S6-T6-U6),0) | W6: =P6-R6-S6-T6+U6 | X6: =MAX(C6-N6-S6,0) | Y6: =MAX(D6-R6,0) | Z6: =MAX(E6+K6-T6,0) | AA6: =MAX(F6-O6+U6,0)
A7: 2028 | B7: =U6 | C7: =V6 | D7: =W6 | E7: =X6 | F7: =Y6 | G7: ='operating_model'!$E17 | H7: =C7*'debt_setup'!$B9 | I7: =D7*'debt_setup'!$C9 | J7: =E7*'historicals_input'!$B31 | K7: =E7*'historicals_input'!$B32 | L7: =F7*'historicals_input'!$B33 | M7: =B7+G7-H7-I7-J7-L7 | N7: =MIN(C7*'debt_setup'!$B11,C7) | O7: =MIN(MAX(M7-N7-'historicals_input'!$B22,0),F7) | P7: =M7-N7-O7 | Q7: =MAX(P7-'historicals_input'!$B22,0)*'historicals_input'!$B36 | R7: =MIN(Q7,D7) | S7: =MIN(MAX(Q7-R7,0),MAX(C7-N7,0)) | T7: =MIN(MAX(Q7-R7-S7,0),E7+K7) | U7: =MIN(MAX('historicals_input'!$B22-(P7-R7-S7-T7),0),MAX('historicals_input'!$B34-F7+O7,0)) | V7: =MAX('historicals_input'!$B22-(P7-R7-S7-T7-U7),0) | W7: =P7-R7-S7-T7+U7 | X7: =MAX(C7-N7-S7,0) | Y7: =MAX(D7-R7,0) | Z7: =MAX(E7+K7-T7,0) | AA7: =MAX(F7-O7+U7,0)
A8: 2029 | B8: =U7 | C8: =V7 | D8: =W7 | E8: =X7 | F8: =Y7 | G8: ='operating_model'!$F17 | H8: =C8*'debt_setup'!$B9 | I8: =D8*'debt_setup'!$C9 | J8: =E8*'historicals_input'!$B31 | K8: =E8*'historicals_input'!$B32 | L8: =F8*'historicals_input'!$B33 | M8: =B8+G8-H8-I8-J8-L8 | N8: =MIN(C8*'debt_setup'!$B11,C8) | O8: =MIN(MAX(M8-N8-'historicals_input'!$B22,0),F8) | P8: =M8-N8-O8 | Q8: =MAX(P8-'historicals_input'!$B22,0)*'historicals_input'!$B36 | R8: =MIN(Q8,D8) | S8: =MIN(MAX(Q8-R8,0),MAX(C8-N8,0)) | T8: =MIN(MAX(Q8-R8-S8,0),E8+K8) | U8: =MIN(MAX('historicals_input'!$B22-(P8-R8-S8-T8),0),MAX('historicals_input'!$B34-F8+O8,0)) | V8: =MAX('historicals_input'!$B22-(P8-R8-S8-T8-U8),0) | W8: =P8-R8-S8-T8+U8 | X8: =MAX(C8-N8-S8,0) | Y8: =MAX(D8-R8,0) | Z8: =MAX(E8+K8-T8,0) | AA8: =MAX(F8-O8+U8,0)

Sheet returns
A1: LBO Returns
A3: Metric | B3: Value
A4: Entry EV | B4: ='sources_uses'!$B5
A5: Entry TLA Debt | B5: ='sources_uses'!$B$14
A6: Entry TLB Debt | B6: ='sources_uses'!$B$15
A7: Entry Sub Debt | B7: ='sources_uses'!$B16
A8: Entry Net Debt | B8: =SUM(B5:B7)
A9: Sponsor Equity | B9: ='sources_uses'!$B19
A10: Entry Debt / EBITDA | B10: =IFERROR(B8/'historicals_input'!$B13,0)
A11: Exit EBITDA | B11: ='operating_model'!$F7
A12: Exit Multiple | B12: ='historicals_input'!$B45
A13: Exit EV | B13: =B11*B12
A14: Exit TLA Debt | B14: ='debt_schedule'!$X8
A15: Exit TLB Debt | B15: ='debt_schedule'!$Y8
A16: Exit Sub Debt | B16: ='debt_schedule'!$Z8
A17: Exit Revolver | B17: ='debt_schedule'!$AA8
A18: Exit Cash | B18: ='debt_schedule'!$W8
A19: Exit Net Debt | B19: =SUM(B14:B17)-B18
A20: Exit Debt / EBITDA | B20: =IFERROR(B19/B11,0)
A21: Debt Paydown | B21: =B8-B19
A22: Exit Equity Value | B22: =B13-SUM(B14:B17)+B18
A23: MOIC | B23: =IFERROR(B22/B9,0)
A24: IRR | B24: =IFERROR(B23^(1/5)-1,0)
A25: Revenue CAGR | B25: =IFERROR((operating_model!F4/historicals_input!B7)^(1/5)-1,0)
A26: EBITDA CAGR | B26: =IFERROR((B11/historicals_input!C7)^(1/5)-1,0)

Sheet valuation
A1: Valuation
A3: WACC | D3: DCF
A4: Metric | B4: Value | D4: Metric | E4: 2025E | F4: 2026E | G4: 2027E | H4: 2028E | I4: 2029E | J4: Total
A5: Risk Free Rate | B5: ='historicals_input'!$B40 | D5: UFCF | E5: ='operating_model'!$B17 | F5: ='operating_model'!$C17 | G5: ='operating_model'!$D17 | H5: ='operating_model'!$E17 | I5: ='operating_model'!$F17
A6: Beta | B6: ='historicals_input'!$B41 | D6: Discount Factor | E6: =1/(1+'valuation'!$B14)^1 | F6: =1/(1+'valuation'!$B14)^2 | G6: =1/(1+'valuation'!$B14)^3 | H6: =1/(1+'valuation'!$B14)^4 | I6: =1/(1+'valuation'!$B14)^5
A7: Market Risk Premium | B7: ='historicals_input'!$B42 | D7: PV of UFCF | E7: =E5*E6 | F7: =F5*F6 | G7: =G5*G6 | H7: =H5*H6 | I7: =I5*I6
A8: Cost of Equity | B8: =B5+B6*B7
A9: Pre-Tax Cost of Debt | B9: ='historicals_input'!$B43 | D9: Terminal Growth | E9: ='historicals_input'!$B44
A10: Tax Rate | B10: ='historicals_input'!$B39 | D10: Exit Multiple | E10: ='historicals_input'!$B45
A11: After-Tax Cost of Debt | B11: =B9*(1-B10) | D11: Terminal Value (PGR) | E11: =(I5*(1+E9))/MAX('valuation'!$B14-E9,0.0001)
A12: Equity Weight | B12: ='returns'!$B9/('returns'!$B9+'sources_uses'!$B$14+'sources_uses'!$B$15+'sources_uses'!$B16) | D12: Terminal Value (Multiple) | E12: ='operating_model'!$F7*E10
A13: Debt Weight | B13: =1-B12 | D13: PV Terminal Value (PGR) | E13: =E11/(1+'valuation'!$B14)^5
A14: WACC | B14: =B12*B8+B13*B11 | D14: PV Terminal Value (Multiple) | E14: =E12/(1+'valuation'!$B14)^5
D15: PV Explicit Period | E15: =SUM(E7:I7)
D16: Enterprise Value (PGR) | E16: =E15+E13
D17: Enterprise Value (Multiple) | E17: =E15+E14
D18: Equity Value (PGR) | E18: =E16-'debt_schedule'!$X$8+'debt_schedule'!$Y$8-'debt_schedule'!$Z8-'debt_schedule'!$AA8+'debt_schedule'!$W8
D19: Equity Value (Multiple) | E19: =E17-'debt_schedule'!$X$8+'debt_schedule'!$Y$8-'debt_schedule'!$Z8-'debt_schedule'!$AA8+'debt_schedule'!$W8
D20: Share Price (PGR) | E20: =E18/'historicals_input'!$B12
D21: Share Price (Multiple) | E21: =E19/'historicals_input'!$B12

Sheet sensitivities
A1: Sensitivities
A3: DCF: WACC vs Terminal Growth
A5: WACC \ Growth | B5: 0.015 | C5: 0.02 | D5: 0.025 | E5: 0.03 | F5: 0.035
A6: 0.104 | B6: =(SUMPRODUCT(valuation!E5:I5,1/(1+A6)^{1,2,3,4,5})+((valuation!I5*(1+B5))/MAX(A6-B5,0.0001))/(1+A6)^5-'debt_schedule'!$X$8+'debt_schedule'!$Y$8-'debt_schedule'!$Z8-'debt_schedule'!$AA8+'debt_schedule'!$W8)/'historicals_input'!$B12 | C6: =(SUMPRODUCT(valuation!E5:I5,1/(1+A6)^{1,2,3,4,5})+((valuation!I5*(1+C5))/MAX(A6-C5,0.0001))/(1+A6)^5-'debt_schedule'!$X$8+'debt_schedule'!$Y$8-'debt_schedule'!$Z8-'debt_schedule'!$AA8+'debt_schedule'!$W8)/'historicals_input'!$B12 | D6: =(SUMPRODUCT(valuation!E5:I5,1/(1+A6)^{1,2,3,4,5})+((valuation!I5*(1+D5))/MAX(A6-D5,0.0001))/(1+A6)^5-'debt_schedule'!$X$8+'debt_schedule'!$Y$8-'debt_schedule'!$Z8-'debt_schedule'!$AA8+'debt_schedule'!$W8)/'historicals_input'!$B12 | E6: =(SUMPRODUCT(valuation!E5:I5,1/(1+A6)^{1,2,3,4,5})+((valuation!I5*(1+E5))/MAX(A6-E5,0.0001))/(1+A6)^5-'debt_schedule'!$X$8+'debt_schedule'!$Y$8-'debt_schedule'!$Z8-'debt_schedule'!$AA8+'debt_schedule'!$W8)/'historicals_input'!$B12 | F6: =(SUMPRODUCT(valuation!E5:I5,1/(1+A6)^{1,2,3,4,5})+((valuation!I5*(1+F5))/MAX(A6-F5,0.0001))/(1+A6)^5-'debt_schedule'!$X$8+'debt_schedule'!$Y$8-'debt_schedule'!$Z8-'debt_schedule'!$AA8+'debt_schedule'!$W8)/'historicals_input'!$B12
A7: 0.109 | B7: =(SUMPRODUCT(valuation!E5:I5,1/(1+A7)^{1,2,3,4,5})+((valuation!I5*(1+B5))/MAX(A7-B5,0.0001))/(1+A7)^5-'debt_schedule'!$X$8+'debt_schedule'!$Y$8-'debt_schedule'!$Z8-'debt_schedule'!$AA8+'debt_schedule'!$W8)/'historicals_input'!$B12 | C7: =(SUMPRODUCT(valuation!E5:I5,1/(1+A7)^{1,2,3,4,5})+((valuation!I5*(1+C5))/MAX(A7-C5,0.0001))/(1+A7)^5-'debt_schedule'!$X$8+'debt_schedule'!$Y$8-'debt_schedule'!$Z8-'debt_schedule'!$AA8+'debt_schedule'!$W8)/'historicals_input'!$B12 | D7: =(SUMPRODUCT(valuation!E5:I5,1/(1+A7)^{1,2,3,4,5})+((valuation!I5*(1+D5))/MAX(A7-D5,0.0001))/(1+A7)^5-'debt_schedule'!$X$8+'debt_schedule'!$Y$8-'debt_schedule'!$Z8-'debt_schedule'!$AA8+'debt_schedule'!$W8)/'historicals_input'!$B12 | E7: =(SUMPRODUCT(valuation!E5:I5,1/(1+A7)^{1,2,3,4,5})+((valuation!I5*(1+E5))/MAX(A7-E5,0.0001))/(1+A7)^5-'debt_schedule'!$X$8+'debt_schedule'!$Y$8-'debt_schedule'!$Z8-'debt_schedule'!$AA8+'debt_schedule'!$W8)/'historicals_input'!$B12 | F7: =(SUMPRODUCT(valuation!E5:I5,1/(1+A7)^{1,2,3,4,5})+((valuation!I5*(1+F5))/MAX(A7-F5,0.0001))/(1+A7)^5-'debt_schedule'!$X$8+'debt_schedule'!$Y$8-'debt_schedule'!$Z8-'debt_schedule'!$AA8+'debt_schedule'!$W8)/'historicals_input'!$B12
A8: 0.114 | B8: =(SUMPRODUCT(valuation!E5:I5,1/(1+A8)^{1,2,3,4,5})+((valuation!I5*(1+B5))/MAX(A8-B5,0.0001))/(1+A8)^5-'debt_schedule'!$X$8+'debt_schedule'!$Y$8-'debt_schedule'!$Z8-'debt_schedule'!$AA8+'debt_schedule'!$W8)/'historicals_input'!$B12 | C8: =(SUMPRODUCT(valuation!E5:I5,1/(1+A8)^{1,2,3,4,5})+((valuation!I5*(1+C5))/MAX(A8-C5,0.0001))/(1+A8)^5-'debt_schedule'!$X$8+'debt_schedule'!$Y$8-'debt_schedule'!$Z8-'debt_schedule'!$AA8+'debt_schedule'!$W8)/'historicals_input'!$B12 | D8: =(SUMPRODUCT(valuation!E5:I5,1/(1+A8)^{1,2,3,4,5})+((valuation!I5*(1+D5))/MAX(A8-D5,0.0001))/(1+A8)^5-'debt_schedule'!$X$8+'debt_schedule'!$Y$8-'debt_schedule'!$Z8-'debt_schedule'!$AA8+'debt_schedule'!$W8)/'historicals_input'!$B12 | E8: =(SUMPRODUCT(valuation!E5:I5,1/(1+A8)^{1,2,3,4,5})+((valuation!I5*(1+E5))/MAX(A8-E5,0.0001))/(1+A8)^5-'debt_schedule'!$X$8+'debt_schedule'!$Y$8-'debt_schedule'!$Z8-'debt_schedule'!$AA8+'debt_schedule'!$W8)/'historicals_input'!$B12 | F8: =(SUMPRODUCT(valuation!E5:I5,1/(1+A8)^{1,2,3,4,5})+((valuation!I5*(1+F5))/MAX(A8-F5,0.0001))/(1+A8)^5-'debt_schedule'!$X$8+'debt_schedule'!$Y$8-'debt_schedule'!$Z8-'debt_schedule'!$AA8+'debt_schedule'!$W8)/'historicals_input'!$B12
A9: 0.119 | B9: =(SUMPRODUCT(valuation!E5:I5,1/(1+A9)^{1,2,3,4,5})+((valuation!I5*(1+B5))/MAX(A9-B5,0.0001))/(1+A9)^5-'debt_schedule'!$X$8+'debt_schedule'!$Y$8-'debt_schedule'!$Z8-'debt_schedule'!$AA8+'debt_schedule'!$W8)/'historicals_input'!$B12 | C9: =(SUMPRODUCT(valuation!E5:I5,1/(1+A9)^{1,2,3,4,5})+((valuation!I5*(1+C5))/MAX(A9-C5,0.0001))/(1+A9)^5-'debt_schedule'!$X$8+'debt_schedule'!$Y$8-'debt_schedule'!$Z8-'debt_schedule'!$AA8+'debt_schedule'!$W8)/'historicals_input'!$B12 | D9: =(SUMPRODUCT(valuation!E5:I5,1/(1+A9)^{1,2,3,4,5})+((valuation!I5*(1+D5))/MAX(A9-D5,0.0001))/(1+A9)^5-'debt_schedule'!$X$8+'debt_schedule'!$Y$8-'debt_schedule'!$Z8-'debt_schedule'!$AA8+'debt_schedule'!$W8)/'historicals_input'!$B12 | E9: =(SUMPRODUCT(valuation!E5:I5,1/(1+A9)^{1,2,3,4,5})+((valuation!I5*(1+E5))/MAX(A9-E5,0.0001))/(1+A9)^5-'debt_schedule'!$X$8+'debt_schedule'!$Y$8-'debt_schedule'!$Z8-'debt_schedule'!$AA8+'debt_schedule'!$W8)/'historicals_input'!$B12 | F9: =(SUMPRODUCT(valuation!E5:I5,1/(1+A9)^{1,2,3,4,5})+((valuation!I5*(1+F5))/MAX(A9-F5,0.0001))/(1+A9)^5-'debt_schedule'!$X$8+'debt_schedule'!$Y$8-'debt_schedule'!$Z8-'debt_schedule'!$AA8+'debt_schedule'!$W8)/'historicals_input'!$B12
A10: 0.124 | B10: =(SUMPRODUCT(valuation!E5:I5,1/(1+A10)^{1,2,3,4,5})+((valuation!I5*(1+B5))/MAX(A10-B5,0.0001))/(1+A10)^5-'debt_schedule'!$X$8+'debt_schedule'!$Y$8-'debt_schedule'!$Z8-'debt_schedule'!$AA8+'debt_schedule'!$W8)/'historicals_input'!$B12 | C10: =(SUMPRODUCT(valuation!E5:I5,1/(1+A10)^{1,2,3,4,5})+((valuation!I5*(1+C5))/MAX(A10-C5,0.0001))/(1+A10)^5-'debt_schedule'!$X$8+'debt_schedule'!$Y$8-'debt_schedule'!$Z8-'debt_schedule'!$AA8+'debt_schedule'!$W8)/'historicals_input'!$B12 | D10: =(SUMPRODUCT(valuation!E5:I5,1/(1+A10)^{1,2,3,4,5})+((valuation!I5*(1+D5))/MAX(A10-D5,0.0001))/(1+A10)^5-'debt_schedule'!$X$8+'debt_schedule'!$Y$8-'debt_schedule'!$Z8-'debt_schedule'!$AA8+'debt_schedule'!$W8)/'historicals_input'!$B12 | E10: =(SUMPRODUCT(valuation!E5:I5,1/(1+A10)^{1,2,3,4,5})+((valuation!I5*(1+E5))/MAX(A10-E5,0.0001))/(1+A10)^5-'debt_schedule'!$X$8+'debt_schedule'!$Y$8-'debt_schedule'!$Z8-'debt_schedule'!$AA8+'debt_schedule'!$W8)/'historicals_input'!$B12 | F10: =(SUMPRODUCT(valuation!E5:I5,1/(1+A10)^{1,2,3,4,5})+((valuation!I5*(1+F5))/MAX(A10-F5,0.0001))/(1+A10)^5-'debt_schedule'!$X$8+'debt_schedule'!$Y$8-'debt_schedule'!$Z8-'debt_schedule'!$AA8+'debt_schedule'!$W8)/'historicals_input'!$B12
A13: LBO: Exit Multiple vs Exit EBITDA Adj.
A15: Exit Multiple \ EBITDA Adj. | B15: -0.1 | C15: -0.05 | D15: 0 | E15: 0.05 | F15: 0.1
A16: 9 | B16: =((('returns'!$B11*(1+B15))*A16)-'debt_schedule'!$X$8+'debt_schedule'!$Y$8-'debt_schedule'!$Z8-'debt_schedule'!$AA8+'debt_schedule'!$W8)/'returns'!$B9 | C16: =((('returns'!$B11*(1+C15))*A16)-'debt_schedule'!$X$8+'debt_schedule'!$Y$8-'debt_schedule'!$Z8-'debt_schedule'!$AA8+'debt_schedule'!$W8)/'returns'!$B9 | D16: =((('returns'!$B11*(1+D15))*A16)-'debt_schedule'!$X$8+'debt_schedule'!$Y$8-'debt_schedule'!$Z8-'debt_schedule'!$AA8+'debt_schedule'!$W8)/'returns'!$B9 | E16: =((('returns'!$B11*(1+E15))*A16)-'debt_schedule'!$X$8+'debt_schedule'!$Y$8-'debt_schedule'!$Z8-'debt_schedule'!$AA8+'debt_schedule'!$W8)/'returns'!$B9 | F16: =((('returns'!$B11*(1+F15))*A16)-'debt_schedule'!$X$8+'debt_schedule'!$Y$8-'debt_schedule'!$Z8-'debt_schedule'!$AA8+'debt_schedule'!$W8)/'returns'!$B9
A17: 9.5 | B17: =((('returns'!$B11*(1+B15))*A17)-'debt_schedule'!$X$8+'debt_schedule'!$Y$8-'debt_schedule'!$Z8-'debt_schedule'!$AA8+'debt_schedule'!$W8)/'returns'!$B9 | C17: =((('returns'!$B11*(1+C15))*A17)-'debt_schedule'!$X$8+'debt_schedule'!$Y$8-'debt_schedule'!$Z8-'debt_schedule'!$AA8+'debt_schedule'!$W8)/'returns'!$B9 | D17: =((('returns'!$B11*(1+D15))*A17)-'debt_schedule'!$X$8+'debt_schedule'!$Y$8-'debt_schedule'!$Z8-'debt_schedule'!$AA8+'debt_schedule'!$W8)/'returns'!$B9 | E17: =((('returns'!$B11*(1+E15))*A17)-'debt_schedule'!$X$8+'debt_schedule'!$Y$8-'debt_schedule'!$Z8-'debt_schedule'!$AA8+'debt_schedule'!$W8)/'returns'!$B9 | F17: =((('returns'!$B11*(1+F15))*A17)-'debt_schedule'!$X$8+'debt_schedule'!$Y$8-'debt_schedule'!$Z8-'debt_schedule'!$AA8+'debt_schedule'!$W8)/'returns'!$B9
A18: 10 | B18: =((('returns'!$B11*(1+B15))*A18)-'debt_schedule'!$X$8+'debt_schedule'!$Y$8-'debt_schedule'!$Z8-'debt_schedule'!$AA8+'debt_schedule'!$W8)/'returns'!$B9 | C18: =((('returns'!$B11*(1+C15))*A18)-'debt_schedule'!$X$8+'debt_schedule'!$Y$8-'debt_schedule'!$Z8-'debt_schedule'!$AA8+'debt_schedule'!$W8)/'returns'!$B9 | D18: =((('returns'!$B11*(1+D15))*A18)-'debt_schedule'!$X$8+'debt_schedule'!$Y$8-'debt_schedule'!$Z8-'debt_schedule'!$AA8+'debt_schedule'!$W8)/'returns'!$B9 | E18: =((('returns'!$B11*(1+E15))*A18)-'debt_schedule'!$X$8+'debt_schedule'!$Y$8-'debt_schedule'!$Z8-'debt_schedule'!$AA8+'debt_schedule'!$W8)/'returns'!$B9 | F18: =((('returns'!$B11*(1+F15))*A18)-'debt_schedule'!$X$8+'debt_schedule'!$Y$8-'debt_schedule'!$Z8-'debt_schedule'!$AA8+'debt_schedule'!$W8)/'returns'!$B9
A19: 10.5 | B19: =((('returns'!$B11*(1+B15))*A19)-'debt_schedule'!$X$8+'debt_schedule'!$Y$8-'debt_schedule'!$Z8-'debt_schedule'!$AA8+'debt_schedule'!$W8)/'returns'!$B9 | C19: =((('returns'!$B11*(1+C15))*A19)-'debt_schedule'!$X$8+'debt_schedule'!$Y$8-'debt_schedule'!$Z8-'debt_schedule'!$AA8+'debt_schedule'!$W8)/'returns'!$B9 | D19: =((('returns'!$B11*(1+D15))*A19)-'debt_schedule'!$X$8+'debt_schedule'!$Y$8-'debt_schedule'!$Z8-'debt_schedule'!$AA8+'debt_schedule'!$W8)/'returns'!$B9 | E19: =((('returns'!$B11*(1+E15))*A19)-'debt_schedule'!$X$8+'debt_schedule'!$Y$8-'debt_schedule'!$Z8-'debt_schedule'!$AA8+'debt_schedule'!$W8)/'returns'!$B9 | F19: =((('returns'!$B11*(1+F15))*A19)-'debt_schedule'!$X$8+'debt_schedule'!$Y$8-'debt_schedule'!$Z8-'debt_schedule'!$AA8+'debt_schedule'!$W8)/'returns'!$B9
A20: 11 | B20: =((('returns'!$B11*(1+B15))*A20)-'debt_schedule'!$X$8+'debt_schedule'!$Y$8-'debt_schedule'!$Z8-'debt_schedule'!$AA8+'debt_schedule'!$W8)/'returns'!$B9 | C20: =((('returns'!$B11*(1+C15))*A20)-'debt_schedule'!$X$8+'debt_schedule'!$Y$8-'debt_schedule'!$Z8-'debt_schedule'!$AA8+'debt_schedule'!$W8)/'returns'!$B9 | D20: =((('returns'!$B11*(1+D15))*A20)-'debt_schedule'!$X$8+'debt_schedule'!$Y$8-'debt_schedule'!$Z8-'debt_schedule'!$AA8+'debt_schedule'!$W8)/'returns'!$B9 | E20: =((('returns'!$B11*(1+E15))*A20)-'debt_schedule'!$X$8+'debt_schedule'!$Y$8-'debt_schedule'!$Z8-'debt_schedule'!$AA8+'debt_schedule'!$W8)/'returns'!$B9 | F20: =((('returns'!$B11*(1+F15))*A20)-'debt_schedule'!$X$8+'debt_schedule'!$Y$8-'debt_schedule'!$Z8-'debt_schedule'!$AA8+'debt_schedule'!$W8)/'returns'!$B9

Sheet checks
A1: Model Checks
A3: Check | B3: Formula | C3: Status
A4: Sources = Uses | B4: =ABS('sources_uses'!$B20-'sources_uses'!$B10) | C4: =IF(B4<1,"PASS","FAIL")
A5: Sponsor Equity Positive | B5: ='sources_uses'!$B19 | C5: =IF(B5>0,"PASS","FAIL")
A6: Minimum Cash Maintained | B6: =MIN('debt_schedule'!$W4,'debt_schedule'!$W5,'debt_schedule'!$W6,'debt_schedule'!$W7,'debt_schedule'!$W8)-'historicals_input'!$B22 | C6: =IF(B6>=0,"PASS","FAIL")
A7: No Negative Senior Debt | B7: =MIN('debt_schedule'!$X$4+'debt_schedule'!$Y$4,'debt_schedule'!$X$5+'debt_schedule'!$Y$5,'debt_schedule'!$X$6+'debt_schedule'!$Y$6,'debt_schedule'!$X$7+'debt_schedule'!$Y$7,'debt_schedule'!$X$8+'debt_schedule'!$Y$8) | C7: =IF(B7>=0,"PASS","FAIL")
A8: No Negative Sub Debt | B8: =MIN('debt_schedule'!$Z4,'debt_schedule'!$Z5,'debt_schedule'!$Z6,'debt_schedule'!$Z7,'debt_schedule'!$Z8) | C8: =IF(B8>=0,"PASS","FAIL")
A9: WACC > Terminal Growth | B9: ='valuation'!$B14-'historicals_input'!$B44 | C9: =IF(B9>0,"PASS","FAIL")
A10: Exit Equity Positive | B10: ='returns'!$B22 | C10: =IF(B10>0,"PASS","FAIL")
A11: DCF Share Price Positive | B11: ='valuation'!$E21 | C11: =IF(B11>0,"PASS","FAIL")
A12: Liquidity Shortfall = 0 | B12: =MAX('debt_schedule'!$V4,'debt_schedule'!$V5,'debt_schedule'!$V6,'debt_schedule'!$V7,'debt_schedule'!$V8) | C12: =IF(B12=0,"PASS","FAIL")
A13: Revolver Within Limit | B13: =MAX('debt_schedule'!$AA4,'debt_schedule'!$AA5,'debt_schedule'!$AA6,'debt_schedule'!$AA7,'debt_schedule'!$AA8)-'historicals_input'!$B34 | C13: =IF(B13<=0,"PASS","FAIL")
A16: Python Safety Snapshot
A17: Metric | B17: Python | C17: Excel | D17: Delta
A18: DCF Share Price (PGR) | B18: 93.692095 | C18: ='valuation'!$E20 | D18: =C18-B18
A19: DCF Share Price (Multiple) | B19: 91.128983 | C19: ='valuation'!$E21 | D19: =C19-B19

Sheet dense_model
A1: Dense Model Snapshot
A3: Transaction Summary | D3: Operating Model
A4: Metric | B4: Value | D4: Metric | E4: 2025E | F4: 2026E | G4: 2027E | H4: 2028E | I4: 2029E
A5: Purchase Price | B5: ='sources_uses'!$B5 | D5: Revenue | E5: =operating_model!B4 | F5: =operating_model!C4 | G5: =operating_model!D4 | H5: =operating_model!E4 | I5: =operating_model!F4
A6: Refinanced Debt | B6: ='sources_uses'!$B6 | D6: EBITDA | E6: =operating_model!B7 | F6: =operating_model!C7 | G6: =operating_model!D7 | H6: =operating_model!E7 | I6: =operating_model!F7
A7: Sponsor Equity | B7: ='sources_uses'!$B19 | D7: UFCF | E7: =operating_model!B17 | F7: =operating_model!C17 | G7: =operating_model!D17 | H7: =operating_model!E17 | I7: =operating_model!F17
A8: Entry EV | B8: ='returns'!$B4
A9: Exit EV | B9: ='returns'!$B13
A10: Exit Equity | B10: ='returns'!$B22 | D10: Debt Roll-Forward
A11: MOIC | B11: ='returns'!$B23 | D11: Metric | E11: 2025E | F11: 2026E | G11: 2027E | H11: 2028E | I11: 2029E
A12: IRR | B12: ='returns'!$B24 | D12: End TLA | E12: =debt_schedule!X4 | F12: =debt_schedule!X5 | G12: =debt_schedule!X6 | H12: =debt_schedule!X7 | I12: =debt_schedule!X8
A13: DCF Share Price | B13: ='valuation'!$E21 | D13: End TLB | E13: =debt_schedule!Y4 | F13: =debt_schedule!Y5 | G13: =debt_schedule!Y6 | H13: =debt_schedule!Y7 | I13: =debt_schedule!Y8
D14: End Sub Debt | E14: =debt_schedule!Z4 | F14: =debt_schedule!Z5 | G14: =debt_schedule!Z6 | H14: =debt_schedule!Z7 | I14: =debt_schedule!Z8
D15: End Revolver | E15: =debt_schedule!AA4 | F15: =debt_schedule!AA5 | G15: =debt_schedule!AA6 | H15: =debt_schedule!AA7 | I15: =debt_schedule!AA8
D16: End Cash | E16: =debt_schedule!W4 | F16: =debt_schedule!W5 | G16: =debt_schedule!W6 | H16: =debt_schedule!W7 | I16: =debt_schedule!W8
D18: Sensitivity Snapshot
D19: Avg DCF Matrix | E19: =AVERAGE(sensitivities!B6:F10)
D20: Avg LBO Matrix | E20: =AVERAGE(sensitivities!B16:F20)
